planetary_computer/__init__.py
planetary_computer/_adlfs.py
planetary_computer/sas.py
planetary_computer/settings.py
planetary_computer/utils.py
planetary_computer/version.py
planetary_computer/scripts/__init__.py
planetary_computer/scripts/cli.py
planetary_computer-1.0.0.dist-info/LICENSE
planetary_computer-1.0.0.dist-info/METADATA
planetary_computer-1.0.0.dist-info/WHEEL
planetary_computer-1.0.0.dist-info/entry_points.txt
planetary_computer-1.0.0.dist-info/top_level.txt
planetary_computer-1.0.0.dist-info/RECORD
