Metadata-Version: 2.1
Name: planetary-computer
Version: 1.0.0
Summary: Planetary Computer SDK for Python
Author-email: microsoft <planetarycomputer@microsoft.com>
License:     MIT License
Requires-Python: >=3.7
Provides-Extra: adlfs
Provides-Extra: azure
Provides-Extra: dev
License-File: LICENSE
